AUTHORS
COPYING.txt
ChangeLog
MANIFEST.in
README.md
requirements.txt
setup.cfg
setup.py
example_profile/ipython_config.py
example_profile/ipython_nbconvert_config.py
example_profile/ipython_notebook_config.py
ipylogue/__init__.py
ipylogue/gitmanager.py
ipylogue.egg-info/PKG-INFO
ipylogue.egg-info/SOURCES.txt
ipylogue.egg-info/dependency_links.txt
ipylogue.egg-info/not-zip-safe
ipylogue.egg-info/requires.txt
ipylogue.egg-info/top_level.txt