Metadata-Version: 1.1
Name: ipylogue
Version: 1.0.0
Summary: Save the history of your IPython notebooks with git
Home-page: UNKNOWN
Author: Ryan S. Brown
Author-email: sb@ryansb.com
License: AGPLv3+
Keywords: ipython
Platform: UNKNOWN
Classifier: Natural Language :: English
Classifier: Development Status :: 3 - Alpha
Classifier: Intended Audience :: Developers
Classifier: Framework :: IPython
Classifier: License :: OSI Approved :: GNU Affero General Public License v3
Classifier: Programming Language :: Python :: 2.7
